{
    "codeToName": {
        "32": "space",
        "33": "exclam",
        "34": "quotedbl",
        "35": "numbersign",
        "36": "dollar",
        "37": "percent",
        "38": "ampersand",
        "39": "quotesingle",
        "40": "parenleft",
        "41": "parenright",
        "42": "asterisk",
        "43": "plus",
        "44": "comma",
        "45": "hyphen",
        "46": "period",
        "47": "slash",
        "48": "zero",
        "49": "one",
        "50": "two",
        "51": "three",
        "52": "four",
        "53": "five",
        "54": "six",
        "55": "seven",
        "56": "eight",
        "57": "nine",
        "58": "colon",
        "59": "semicolon",
        "60": "less",
        "61": "equal",
        "62": "greater",
        "63": "question",
        "64": "at",
        "65": "A",
        "66": "B",
        "67": "C",
        "68": "D",
        "69": "E",
        "70": "F",
        "71": "G",
        "72": "H",
        "73": "I",
        "74": "J",
        "75": "K",
        "76": "L",
        "77": "M",
        "78": "N",
        "79": "O",
        "80": "P",
        "81": "Q",
        "82": "R",
        "83": "S",
        "84": "T",
        "85": "U",
        "86": "V",
        "87": "W",
        "88": "X",
        "89": "Y",
        "90": "Z",
        "91": "bracketleft",
        "92": "backslash",
        "93": "bracketright",
        "94": "asciicircum",
        "95": "underscore",
        "96": "grave",
        "97": "a",
        "98": "b",
        "99": "c",
        "100": "d",
        "101": "e",
        "102": "f",
        "103": "g",
        "104": "h",
        "105": "i",
        "106": "j",
        "107": "k",
        "108": "l",
        "109": "m",
        "110": "n",
        "111": "o",
        "112": "p",
        "113": "q",
        "114": "r",
        "115": "s",
        "116": "t",
        "117": "u",
        "118": "v",
        "119": "w",
        "120": "x",
        "121": "y",
        "122": "z",
        "123": "braceleft",
        "124": "bar",
        "125": "braceright",
        "126": "asciitilde",
        "160": "nbspace",
        "161": "exclamdown",
        "162": "cent",
        "163": "sterling",
        "164": "currency",
        "165": "yen",
        "166": "brokenbar",
        "167": "section",
        "168": "dieresis",
        "169": "copyright",
        "170": "ordfeminine",
        "171": "guillemotleft",
        "172": "logicalnot",
        "173": "sfthyphen",
        "174": "registered",
        "175": "overscore",
        "176": "degree",
        "177": "plusminus",
        "178": "twosuperior",
        "179": "threesuperior",
        "180": "acute",
        "181": "mu",
        "182": "paragraph",
        "183": "middot",
        "184": "cedilla",
        "185": "onesuperior",
        "186": "ordmasculine",
        "187": "guillemotright",
        "188": "onequarter",
        "189": "onehalf",
        "190": "threequarters",
        "191": "questiondown",
        "192": "Agrave",
        "193": "Aacute",
        "194": "Acircumflex",
        "195": "Atilde",
        "196": "Adieresis",
        "197": "Aring",
        "198": "AE",
        "199": "Ccedilla",
        "200": "Egrave",
        "201": "Eacute",
        "202": "Ecircumflex",
        "203": "Edieresis",
        "204": "Igrave",
        "205": "Iacute",
        "206": "Icircumflex",
        "207": "Idieresis",
        "208": "Eth",
        "209": "Ntilde",
        "210": "Ograve",
        "211": "Oacute",
        "212": "Ocircumflex",
        "213": "Otilde",
        "214": "Odieresis",
        "215": "multiply",
        "216": "Oslash",
        "217": "Ugrave",
        "218": "Uacute",
        "219": "Ucircumflex",
        "220": "Udieresis",
        "221": "Yacute",
        "222": "Thorn",
        "223": "germandbls",
        "224": "agrave",
        "225": "aacute",
        "226": "acircumflex",
        "227": "atilde",
        "228": "adieresis",
        "229": "aring",
        "230": "ae",
        "231": "ccedilla",
        "232": "egrave",
        "233": "eacute",
        "234": "ecircumflex",
        "235": "edieresis",
        "236": "igrave",
        "237": "iacute",
        "238": "icircumflex",
        "239": "idieresis",
        "240": "eth",
        "241": "ntilde",
        "242": "ograve",
        "243": "oacute",
        "244": "ocircumflex",
        "245": "otilde",
        "246": "odieresis",
        "247": "divide",
        "248": "oslash",
        "249": "ugrave",
        "250": "uacute",
        "251": "ucircumflex",
        "252": "udieresis",
        "253": "yacute",
        "254": "thorn",
        "255": "ydieresis",
        "262": "Cacute",
        "263": "cacute",
        "268": "Ccaron",
        "269": "ccaron",
        "273": "dmacron",
        "286": "Gbreve",
        "287": "gbreve",
        "304": "Idot",
        "305": "dotlessi",
        "321": "Lslash",
        "322": "lslash",
        "338": "OE",
        "339": "oe",
        "350": "Scedilla",
        "351": "scedilla",
        "352": "Scaron",
        "353": "scaron",
        "376": "Ydieresis",
        "381": "Zcaron",
        "382": "zcaron",
        "402": "florin",
        "710": "circumflex",
        "711": "caron",
        "713": "macron",
        "728": "breve",
        "729": "dotaccent",
        "730": "ring",
        "731": "ogonek",
        "732": "tilde",
        "733": "hungarumlaut",
        "960": "pi",
        "8211": "endash",
        "8212": "emdash",
        "8216": "quoteleft",
        "8217": "quoteright",
        "8218": "quotesinglbase",
        "8220": "quotedblleft",
        "8221": "quotedblright",
        "8222": "quotedblbase",
        "8224": "dagger",
        "8225": "daggerdbl",
        "8226": "bullet",
        "8230": "ellipsis",
        "8240": "perthousand",
        "8249": "guilsinglleft",
        "8250": "guilsinglright",
        "8355": "franc",
        "8482": "trademark",
        "8486": "Omega",
        "8706": "partialdiff",
        "8710": "Delta",
        "8719": "product",
        "8721": "summation",
        "8722": "minus",
        "8725": "fraction",
        "8729": "periodcentered",
        "8730": "radical",
        "8734": "infinity",
        "8747": "integral",
        "8776": "approxequal",
        "8800": "notequal",
        "8804": "lessequal",
        "8805": "greaterequal",
        "9674": "lozenge",
        "61440": "apple",
        "61441": "fi",
        "61442": "fl"
    },
    "isUnicode": true,
    "EncodingScheme": "FontSpecific",
    "FontName": "PhyllisD",
    "FullName": "PhyllisD",
    "Version": "Version 001.005",
    "PostScriptName": "PhyllisD",
    "Weight": "Medium",
    "ItalicAngle": "200",
    "IsFixedPitch": "false",
    "UnderlineThickness": "28",
    "UnderlinePosition": "-100",
    "FontHeightOffset": "0",
    "Ascender": "943",
    "Descender": "-257",
    "FontBBox": [
        "-158",
        "-268",
        "1090",
        "838"
    ],
    "StartCharMetrics": "306",
    "C": {
        "32": 250,
        "33": 205,
        "34": 220,
        "35": 467,
        "36": 467,
        "37": 459,
        "38": 610,
        "39": 133,
        "40": 281,
        "41": 281,
        "42": 467,
        "43": 467,
        "44": 118,
        "45": 133,
        "46": 91,
        "47": 333,
        "48": 467,
        "49": 467,
        "50": 467,
        "51": 467,
        "52": 467,
        "53": 467,
        "54": 467,
        "55": 467,
        "56": 467,
        "57": 467,
        "58": 153,
        "59": 179,
        "60": 500,
        "61": 467,
        "62": 500,
        "63": 348,
        "64": 675,
        "65": 689,
        "66": 717,
        "67": 533,
        "68": 734,
        "69": 526,
        "70": 620,
        "71": 584,
        "72": 815,
        "73": 583,
        "74": 559,
        "75": 804,
        "76": 725,
        "77": 923,
        "78": 882,
        "79": 604,
        "80": 689,
        "81": 604,
        "82": 711,
        "83": 561,
        "84": 644,
        "85": 820,
        "86": 408,
        "87": 966,
        "88": 416,
        "89": 787,
        "90": 668,
        "91": 281,
        "92": 500,
        "93": 281,
        "94": 500,
        "95": 500,
        "96": 500,
        "97": 357,
        "98": 328,
        "99": 297,
        "100": 345,
        "101": 297,
        "102": 236,
        "103": 333,
        "104": 355,
        "105": 178,
        "106": 167,
        "107": 350,
        "108": 164,
        "109": 502,
        "110": 345,
        "111": 350,
        "112": 346,
        "113": 331,
        "114": 222,
        "115": 261,
        "116": 188,
        "117": 348,
        "118": 345,
        "119": 491,
        "120": 309,
        "121": 347,
        "122": 294,
        "123": 281,
        "124": 500,
        "125": 281,
        "126": 667,
        "160": 250,
        "161": 205,
        "162": 467,
        "163": 467,
        "164": 458,
        "165": 467,
        "166": 500,
        "167": 467,
        "168": 500,
        "169": 750,
        "170": 247,
        "171": 233,
        "172": 500,
        "173": 133,
        "174": 750,
        "175": 500,
        "176": 220,
        "177": 467,
        "178": 304,
        "179": 304,
        "180": 500,
        "181": 348,
        "182": 467,
        "183": 91,
        "184": 500,
        "185": 304,
        "186": 247,
        "187": 233,
        "188": 701,
        "189": 701,
        "190": 701,
        "191": 348,
        "192": 689,
        "193": 689,
        "194": 689,
        "195": 689,
        "196": 689,
        "197": 689,
        "198": 1057,
        "199": 533,
        "200": 526,
        "201": 526,
        "202": 526,
        "203": 526,
        "204": 583,
        "205": 583,
        "206": 583,
        "207": 583,
        "208": 734,
        "209": 882,
        "210": 604,
        "211": 604,
        "212": 604,
        "213": 604,
        "214": 604,
        "215": 467,
        "216": 604,
        "217": 820,
        "218": 820,
        "219": 820,
        "220": 820,
        "221": 787,
        "222": 689,
        "223": 350,
        "224": 357,
        "225": 357,
        "226": 357,
        "227": 357,
        "228": 357,
        "229": 357,
        "230": 533,
        "231": 297,
        "232": 297,
        "233": 297,
        "234": 297,
        "235": 297,
        "236": 191,
        "237": 191,
        "238": 191,
        "239": 191,
        "240": 350,
        "241": 345,
        "242": 350,
        "243": 350,
        "244": 350,
        "245": 350,
        "246": 350,
        "247": 467,
        "248": 351,
        "249": 348,
        "250": 348,
        "251": 348,
        "252": 348,
        "253": 347,
        "254": 346,
        "255": 347,
        "262": 533,
        "263": 297,
        "268": 533,
        "269": 297,
        "273": 345,
        "286": 584,
        "287": 333,
        "304": 583,
        "305": 191,
        "321": 725,
        "322": 164,
        "338": 983,
        "339": 552,
        "350": 561,
        "351": 261,
        "352": 561,
        "353": 261,
        "376": 787,
        "381": 668,
        "382": 294,
        "402": 466,
        "710": 500,
        "711": 500,
        "713": 500,
        "728": 500,
        "729": 500,
        "730": 500,
        "731": 500,
        "732": 500,
        "733": 500,
        "960": 500,
        "8211": 467,
        "8212": 387,
        "8216": 118,
        "8217": 118,
        "8218": 118,
        "8220": 208,
        "8221": 208,
        "8222": 208,
        "8224": 467,
        "8225": 467,
        "8226": 667,
        "8230": 273,
        "8240": 678,
        "8249": 143,
        "8250": 143,
        "8355": 659,
        "8482": 970,
        "8486": 667,
        "8706": 500,
        "8710": 667,
        "8719": 667,
        "8721": 667,
        "8722": 467,
        "8725": 93,
        "8729": 91,
        "8730": 667,
        "8734": 667,
        "8747": 501,
        "8776": 500,
        "8800": 467,
        "8804": 500,
        "8805": 500,
        "9674": 667,
        "61440": 667,
        "61441": 387,
        "61442": 373
    },
    "CIDtoGID_Compressed": true,
    "CIDtoGID": "eJzt0AWzVlUUBuB3S3d3l4Vid2ChGICKAWJ3dyGhWGBgYIABoqCiDAYoiokKdnfHP\/GO8w0zDOCVewc\/ZZ5n5py1Zp8d7z5JPTVIwzRK4zRJ0zRL87RIy7RK67RJ27RL+3RIx3RK53RJ13RL9\/RIz\/RK7\/RJ3\/RL\/wzIwAzKptksm2eLbJnB2SpbZ0i2ybbZLttnh+yYnbJzdsmu2S27Z4\/smb2yd4Zmn+yb\/bJ\/DsiwHJiDMjwH55AcmsMyIiMzKofniByZ0TkqR+eYHJsxGZvjMi7H54ScmJNyck6p7+WTsknm5cbclNdzf2mQm3NHbsvsPJX5pWFuLY1yQ+4pjUuTTM\/MTCtN82tpljl5ujQvLUrLPJZF+SDv5ZmcmtNyV07PRzkj7+fDfJaP80k+La1yZr7K5\/kiz+as0jp359t8nW9ydmlT2uaWnJtzcl4uyPm5MHNzUS7Jxbk0l+WKXJ4rc1Vpl6tzTcZnQiZlYl7Oo7k2k3NdppT2pUNeWe0uHUunVX3n0qXSdV3n3buV7rX+nx75rpYZPUuvWjZ5Ls+vdWXv0qf0Lf1qy7CaV1et7l8G\/MM1T6zXCVA33+ePmvePfzvnp\/ycX\/J7fshv\/04oNqiHqh0AAAAAAAAAAAAAAAAAAPifWpwllW5pXsqKmvpCXszKmnp93s7UyreFa1n57hojb+TNDROyesrAaieoqtsr9ZGqpqCuZlXqgjW+PFjzPFAG\/dW\/Vhl7J49Xuhnr3PHhOmd5cj3n31mp9+a+Op8JAP8Fy6odAAAAAAAAAAAAAAAAAAAAAAAAAAAAAAAAAAAAAAAAAAAAAAAAAAAAAAAAAAAAAAAAAAAAAAAAAAAAAAAAAAAAAAAAAAAAAAAAAAAAAAAAAAAAAAAAAAAAAAAAAAAAAAAAAAAAAGAj8mWW561qhwAAAAAAAAAA6uNPYJBlhQ==",
    "_version_": 6
}